envscan/__init__.py
envscan/cli.py
envscan/detector.py
envscan/utils.py
envscan-0.1.8.dist-info/licenses/LICENSE
envscan-0.1.8.dist-info/METADATA
envscan-0.1.8.dist-info/WHEEL
envscan-0.1.8.dist-info/entry_points.txt
envscan-0.1.8.dist-info/top_level.txt
envscan-0.1.8.dist-info/RECORD
