Metadata-Version: 2.4
Name: envscan
Version: 0.1.8
Summary: Scan directories to find Python virtual environments
Author-email: Vamsee Yashwanth <vamsee.ny1@gmail.com>
License-Expression: MIT
Project-URL: Homepage, https://github.com/VamseeNY/envscan
Project-URL: Repository, https://github.com/VamseeNY/envscan
Project-URL: Documentation, https://github.com/VamseeNY/envscan#readme
Requires-Python: >=3.8
License-File: LICENSE
Requires-Dist: click>=8.0
Provides-Extra: web
Requires-Dist: streamlit>=1.44.1; extra == "web"
Provides-Extra: dev
Requires-Dist: pytest; extra == "dev"
Requires-Dist: pre-commit; extra == "dev"
Dynamic: license-file
